MANIFEST.in
README.rst
setup.py
aliyun_python_sdk_lrg.egg-info/PKG-INFO
aliyun_python_sdk_lrg.egg-info/SOURCES.txt
aliyun_python_sdk_lrg.egg-info/dependency_links.txt
aliyun_python_sdk_lrg.egg-info/requires.txt
aliyun_python_sdk_lrg.egg-info/top_level.txt
aliyunsdklrg/__init__.py
aliyunsdklrg/request/__init__.py
aliyunsdklrg/request/v20191010/AddFailMachineToBlackListRequest.py
aliyunsdklrg/request/v20191010/AddNodeDnResourceRequest.py
aliyunsdklrg/request/v20191010/AddNodeVipResourceRequest.py
aliyunsdklrg/request/v20191010/AddPackageSnapshotRequest.py
aliyunsdklrg/request/v20191010/AppendPropertyOptionsRequest.py
aliyunsdklrg/request/v20191010/ChangeStatusRequest.py
aliyunsdklrg/request/v20191010/CreateNodeRequest.py
aliyunsdklrg/request/v20191010/DeployProcessStatusRequest.py
aliyunsdklrg/request/v20191010/DeployVersionAutoCreateRequest.py
aliyunsdklrg/request/v20191010/FindAllReleaseSetRequest.py
aliyunsdklrg/request/v20191010/GetClusterYamlRequest.py
aliyunsdklrg/request/v20191010/GetDeployUnitRequest.py
aliyunsdklrg/request/v20191010/GetNodeInfoRequest.py
aliyunsdklrg/request/v20191010/GetPropertiesRequest.py
aliyunsdklrg/request/v20191010/GetRoleInfoRequest.py
aliyunsdklrg/request/v20191010/GetRunningMachineListRequest.py
aliyunsdklrg/request/v20191010/GetVersionRequest.py
aliyunsdklrg/request/v20191010/GwGroupUpdateGroupRequest.py
aliyunsdklrg/request/v20191010/GwGroupUpdateStatusRequest.py
aliyunsdklrg/request/v20191010/GwListGatewayRequest.py
aliyunsdklrg/request/v20191010/GwUpdateGatewayIdRequest.py
aliyunsdklrg/request/v20191010/ImportExtraNcToNodeRequest.py
aliyunsdklrg/request/v20191010/ListGroupRequest.py
aliyunsdklrg/request/v20191010/ProcessActionInitRequest.py
aliyunsdklrg/request/v20191010/ProcessActionStartRequest.py
aliyunsdklrg/request/v20191010/ProcessResultRequest.py
aliyunsdklrg/request/v20191010/QueryNodeChildrenRequest.py
aliyunsdklrg/request/v20191010/QueryNodeCurrentVersionRequest.py
aliyunsdklrg/request/v20191010/QueryNodeDeployProcessesRequest.py
aliyunsdklrg/request/v20191010/QueryNodeParentRequest.py
aliyunsdklrg/request/v20191010/QueryProcessByUnitIdRequest.py
aliyunsdklrg/request/v20191010/QueryTagIpWithClusterNameRequest.py
